<?xml version="1.0" encoding="UTF-8"?><s:Envelope xmlns:s="http://www.w3.org/2003/05/soap-envelope" xmlns:a="http://www.w3.org/2005/08/addressing"><s:Header><a:Action s:mustUnderstand="1">http://TekTravel/HotelBookingApi/IHotelService/AvailableHotelRoomsResponse</a:Action></s:Header><s:Body xmlns:xsi="http://www.w3.org/2001/XMLSchema-instance" xmlns:xsd="http://www.w3.org/2001/XMLSchema"><HotelRoomAvailabilityResponse xmlns="http://TekTravel/HotelBookingApi"><Status><StatusCode>01</StatusCode><Description>Successful: AvailableHotelRoom Successful</Description></Status><ResultIndex>14</ResultIndex><HotelRooms><HotelRoom><RoomIndex>1</RoomIndex><RoomTypeName>Double Room - Single Use</RoomTypeName><Inclusion>Breakfast</Inclusion><RoomTypeCode>1490|73371555|1|1^^1^^1490|73371555|3</RoomTypeCode><RatePlanCode>1490|73371555|3</RatePlanCode><RoomRate IsInstantConfirmed="true" B2CRates="false" IsPackageRate="false" Currency="USD" TotalFare="91.78" AgentMarkUp="0.00" RoomFare="91.78" RoomTax="0"><DayRates><DayRate Date="2021-06-27T00:00:00" BaseFare="30.595000"/><DayRate Date="2021-06-28T00:00:00" BaseFare="30.595000"/><DayRate Date="2021-06-29T00:00:00" BaseFare="30.595000"/></DayRates><ExtraGuestCharges>0</ExtraGuestCharges><ChildCharges>0</ChildCharges><Discount>0</Discount><OtherCharges>0</OtherCharges><ServiceTax>0</ServiceTax></RoomRate><RoomPromtion/><Amenities/><MealType>BreakFast</MealType></HotelRoom></HotelRooms><OptionsForBooking><FixedFormat>true</FixedFormat><RoomCombination><RoomIndex>1</RoomIndex></RoomCombination></OptionsForBooking></HotelRoomAvailabilityResponse></s:Body></s:Envelope>